testarium/__init__.py
testarium/coderepos.py
testarium/experiment.py
testarium/filedb.py
testarium/kernel.py
testarium/utils.py
testarium/score/__init__.py
testarium/score/der.py
testarium/score/fafr.py
testarium/web/__init__.py
testarium/web/static/__init__.py
testarium/web/static/favicon.ico
testarium/web/static/fonts/FontAwesome.otf
testarium/web/static/fonts/FontAwesome.ttf
testarium/web/static/fonts/Gudea-Bold.otf
testarium/web/static/fonts/Gudea-Bold.ttf
testarium/web/static/fonts/Gudea-Italic.otf
testarium/web/static/fonts/Gudea-Italic.ttf
testarium/web/static/fonts/Gudea-Regular.otf
testarium/web/static/fonts/Gudea-Regular.ttf
testarium/web/static/fonts/fontawesome-webfont.eot
testarium/web/static/fonts/fontawesome-webfont.svg
testarium/web/static/fonts/fontawesome-webfont.ttf
testarium/web/static/fonts/fontawesome-webfont.woff
testarium/web/static/fonts/fontawesome-webfont.woff2
testarium/web/static/fonts/stylesheet.css
testarium/web/static/images/back.jpg
testarium/web/static/images/tips/help1.jpg
testarium/web/static/images/tips/help2.jpg
testarium/web/static/images/tips/help3.jpg
testarium/web/static/images/tips/help4.jpg
testarium/web/static/images/tips/learningrates.jpeg
testarium/web/static/scripts/d3.linegraph.js
testarium/web/static/scripts/d3.v3.min.js
testarium/web/static/scripts/jquery-ui.min.js
testarium/web/static/scripts/jquery.min.js
testarium/web/static/scripts/jquery.mousewheel.min.js
testarium/web/static/scripts/jsrender.min.js
testarium/web/static/scripts/main.js
testarium/web/static/scripts/wavesurfer.min.js
testarium/web/static/scripts/wavesurfer.regions.js
testarium/web/static/scripts/wavesurfer.spectrogram.js
testarium/web/static/styles/d3.linegraph.css
testarium/web/static/styles/font-awesome.css
testarium/web/static/styles/jquery-ui.min.css
testarium/web/static/styles/main.css
testarium/web/static/styles/images/ui-icons_222222_256x240.png
testarium/web/templates/__init__.py
testarium-0.3.5.dist-info/METADATA
testarium-0.3.5.dist-info/RECORD
testarium-0.3.5.dist-info/WHEEL
testarium-0.3.5.dist-info/top_level.txt
