Metadata-Version: 2.1
Name: testarium
Version: 0.3.5
Summary: Research tool to perform experiments and store results in the repository. More: http://testarium.makseq.com
Home-page: http://testarium.makseq.com
Author: Max Tkachenko, Danila Doroshin, Alexander Yamshinin
Author-email: makseq@gmail.com
License: GNU GPLv3
Keywords: testing,logging,research,science,repository
Platform: UNKNOWN
Classifier: Topic :: Scientific/Engineering
Classifier: Development Status :: 3 - Alpha
Classifier: Operating System :: OS Independent
Classifier: Programming Language :: Python
Classifier: Intended Audience :: Science/Research
Requires-Dist: numpy
Requires-Dist: flask
Requires-Dist: colorama
Requires-Dist: pycrypto
Requires-Dist: argcomplete
